README.rst
setup.py
efb_qq_slave/ClientMgr.py
efb_qq_slave/__init__.py
efb_qq_slave/__version__.py
efb_qq_slave/Clients/BaseClient.py
efb_qq_slave/Clients/__init__.py
efb_qq_slave/Clients/CoolQ/ChatMgr.py
efb_qq_slave/Clients/CoolQ/CoolQ.py
efb_qq_slave/Clients/CoolQ/Exceptions.py
efb_qq_slave/Clients/CoolQ/MsgDecorator.py
efb_qq_slave/Clients/CoolQ/Utils.py
efb_qq_slave/Clients/CoolQ/__init__.py
lmikoto_efb_qq_slave.egg-info/PKG-INFO
lmikoto_efb_qq_slave.egg-info/SOURCES.txt
lmikoto_efb_qq_slave.egg-info/dependency_links.txt
lmikoto_efb_qq_slave.egg-info/entry_points.txt
lmikoto_efb_qq_slave.egg-info/requires.txt
lmikoto_efb_qq_slave.egg-info/top_level.txt