Metadata-Version: 1.2
Name: lmikoto-efb-qq-slave
Version: 2.2.0
Summary: QQ Slave Channel for EH Forwarder Bot, integrated with various QQ Clients.
Home-page: https://github.com/milkice233/efb-qq-slave
Author: Milkice
Author-email: milkice@milkice.me
License: GPLv3
Keywords: ehforwarderbot,EH Forwarder Bot,EH Forwarder Bot Slave Channel,qq,chatbot
Platform: UNKNOWN
Classifier: Development Status :: 3 - Alpha
Classifier: License :: OSI Approved :: GNU General Public License v3 (GPLv3)
Classifier: Intended Audience :: Developers
Classifier: Intended Audience :: End Users/Desktop
Classifier: Programming Language :: Python :: 3 :: Only
Classifier: Programming Language :: Python :: 3.6
Classifier: Programming Language :: Python :: 3.7
Classifier: Topic :: Communications :: Chat
Classifier: Topic :: Utilities
Requires-Python: >=3.6
